{
  "title": "Identificar PlayStation 3",
  "description": "Selecciona el modelo de tu PlayStation 3 para continuar.",
  "models": [
    {
      "id": "fat",
      "name": "PlayStation 3 Fat",
      "code": "Fat / modelo original",
      "image": "/assets/img/consolas/ps3/models/fat.png",
      "compatibility": {
        "modType": "cfw",
        "cfwPossible": true,
        "henOnly": false,
        "ps1Games": true,
        "ps2IsoGames": true
      },
      "message": {
        "type": "note",
        "title": "Nota",
        "text": "Compatible con CFW.",
        "note": "En este flujo se permiten juegos de PS1 y PS2 en formato compatible."
      }
    },
    {
      "id": "slim_20xx",
      "name": "PlayStation 3 Slim CECH-20xx",
      "code": "Slim CECH-20xx",
      "image": "/assets/img/consolas/ps3/models/slim.png",
      "compatibility": {
        "modType": "cfw",
        "cfwPossible": true,
        "henOnly": false,
        "ps1Games": true,
        "ps2IsoGames": true
      },
      "message": {
        "type": "note",
        "title": "Nota",
        "text": "Compatible con CFW.",
        "note": "Este modelo permite habilitar catálogo PS2 dentro del flujo."
      }
    },
    {
      "id": "slim_21xx",
      "name": "PlayStation 3 Slim CECH-21xx",
      "code": "Slim CECH-21xx",
      "image": "/assets/img/consolas/ps3/models/slim.png",
      "compatibility": {
        "modType": "cfw",
        "cfwPossible": true,
        "henOnly": false,
        "ps1Games": true,
        "ps2IsoGames": true
      },
      "message": {
        "type": "note",
        "title": "Nota",
        "text": "Compatible con CFW.",
        "note": "Este modelo permite habilitar catálogo PS2 dentro del flujo."
      }
    },
    {
      "id": "slim_25xx_confirmed_cfw",
      "name": "PlayStation 3 Slim CECH-25xx compatible con CFW",
      "code": "Slim CECH-25xx compatible con CFW",
      "image": "/assets/img/consolas/ps3/models/slim.png",
      "compatibility": {
        "modType": "cfw",
        "cfwPossible": true,
        "henOnly": false,
        "ps1Games": true,
        "ps2IsoGames": true,
        "needsExactModel": true
      },
      "message": {
        "type": "warning",
        "title": "Importante",
        "text": "Solo aplica si ya se confirmó compatibilidad con CFW.",
        "note": "En CECH-25xx la compatibilidad debe verificarse con modelo exacto/BGToolSet/MinVerChk antes de ofrecer PS2 ISO."
      }
    },
    {
      "id": "slim_25xx_not_confirmed",
      "name": "PlayStation 3 Slim CECH-25xx no confirmado",
      "code": "Slim CECH-25xx no confirmado",
      "image": "/assets/img/consolas/ps3/models/slim.png",
      "compatibility": {
        "modType": "unknown",
        "cfwPossible": null,
        "henOnly": null,
        "ps1Games": true,
        "ps2IsoGames": false,
        "needsExactModel": true
      },
      "message": {
        "type": "warning",
        "title": "Importante",
        "text": "La compatibilidad con CFW debe confirmarse antes.",
        "note": "Por seguridad, este flujo no habilita juegos de PS2 ISO hasta confirmar que acepta CFW."
      }
    },
    {
      "id": "slim_30xx",
      "name": "PlayStation 3 Slim CECH-30xx",
      "code": "Slim CECH-30xx",
      "image": "/assets/img/consolas/ps3/models/slim.png",
      "compatibility": {
        "modType": "hen",
        "cfwPossible": false,
        "henOnly": true,
        "ps1Games": true,
        "ps2IsoGames": false
      },
      "message": {
        "type": "warning",
        "title": "Importante",
        "text": "Modelo no compatible con CFW.",
        "note": "No se habilitan juegos de PS2 ISO para este modelo dentro de este flujo."
      }
    },
    {
      "id": "slim_unknown",
      "name": "PlayStation 3 Slim - no sé el modelo exacto",
      "code": "Slim no confirmado",
      "image": "/assets/img/consolas/ps3/models/slim.png",
      "compatibility": {
        "modType": "unknown",
        "cfwPossible": null,
        "henOnly": null,
        "ps1Games": true,
        "ps2IsoGames": false,
        "needsExactModel": true
      },
      "message": {
        "type": "warning",
        "title": "Importante",
        "text": "Necesitamos confirmar el modelo exacto.",
        "note": "Por seguridad, este flujo no habilita juegos de PS2 ISO si no se confirma compatibilidad con CFW."
      }
    },
    {
      "id": "super_slim",
      "name": "PlayStation 3 Super Slim",
      "code": "Super Slim",
      "image": "/assets/img/consolas/ps3/models/super-slim.png",
      "compatibility": {
        "modType": "hen",
        "cfwPossible": false,
        "henOnly": true,
        "ps1Games": true,
        "ps2IsoGames": false
      },
      "message": {
        "type": "warning",
        "title": "Importante",
        "text": "Modelo no compatible con CFW.",
        "note": "No se ofrecen juegos de PS2 en formato ISO para este modelo dentro de este flujo."
      }
    }
  ]
}